{
    "video": {
        "codecs": {
            "avc": {
                "preset": "medium"
            },
            "hevc": {
                "preset": "medium"
            }
        },
        "denoiseOptions": "hqdn3d=4:4:3:3",
        "tonemapOptions": "hable:desat=0"
    },
    "audio": {
        "codecs": {
            "aac": {
                "name":  "aac"
            },
            "ac3": {
                "name": "ac3"
            },
            "heAac": {
                "name": "libfdk_aac",
                "options": "-profile:a aac_he"
            }
        }
    }
}